harmonize/__init__.py
harmonize/exceptions.py
harmonize/player.py
harmonize/py.typed
harmonize/queue.py
harmonize/abstract/__init__.py
harmonize/abstract/filter.py
harmonize/abstract/serializable.py
harmonize/connection/__init__.py
harmonize/connection/node.py
harmonize/connection/pool.py
harmonize/connection/transport.py
harmonize/connection/cache/__init__.py
harmonize/connection/cache/dll.py
harmonize/connection/cache/lfu.py
harmonize/connection/cache/nodes/__init__.py
harmonize/connection/cache/nodes/data.py
harmonize/connection/cache/nodes/dll.py
harmonize/enums/__init__.py
harmonize/enums/cache_capacity.py
harmonize/enums/end_reason.py
harmonize/enums/load_type.py
harmonize/enums/loop_status.py
harmonize/enums/node_status.py
harmonize/enums/severity.py
harmonize/objects/__init__.py
harmonize/objects/load_result.py
harmonize/objects/missing.py
harmonize/objects/playlist_info.py
harmonize/objects/stats.py
harmonize/objects/track.py
harmonize/objects/filters/__init__.py
harmonize/objects/filters/channel_mix.py
harmonize/objects/filters/distortion.py
harmonize/objects/filters/equalizer.py
harmonize/objects/filters/karaoke.py
harmonize/objects/filters/low_pass.py
harmonize/objects/filters/rotation.py
harmonize/objects/filters/timescale.py
harmonize/objects/filters/tremolo.py
harmonize/objects/filters/vibrato.py
harmonize/objects/filters/volume.py
harmonize.py-1.0.0.dist-info/LICENSE
harmonize.py-1.0.0.dist-info/METADATA
harmonize.py-1.0.0.dist-info/WHEEL
harmonize.py-1.0.0.dist-info/top_level.txt
harmonize.py-1.0.0.dist-info/RECORD
